README.rst
setup.py
scripts/until_nonidle
until_nonidle/__init__.py
until_nonidle/until_nonidle.py
until_nonidle.egg-info/PKG-INFO
until_nonidle.egg-info/SOURCES.txt
until_nonidle.egg-info/dependency_links.txt
until_nonidle.egg-info/requires.txt
until_nonidle.egg-info/top_level.txt