Metadata-Version: 1.0
Name: until-nonidle
Version: 0.3
Summary: Execute something as long as the user is idling.
Home-page: http://github.com/enricobacis/until_nonidle
Author: Enrico Bacis
Author-email: enrico.bacis@gmail.com
License: MIT
Keywords: idle lock lockscreen action
Platform: UNKNOWN
